<!DOCTYPE Board_Memory_Definition_File>
<Root name="MKV58F1M0xxx22">
  <MemorySegment size="0x10000" access="Read/Write" start="0x00000000" name="ITCM" />
  <MemorySegment size="0x100000" access="ReadOnly" start="0x10000000" name="FLASH" />
  <MemorySegment size="0x40000" access="Read/Write" start="0x20000000" name="SRAM" />
  <MemorySegment size="0x40000/2" access="Read/Write" start="0x20000000" name="D0TCM" />
  <MemorySegment size="0x40000/2" access="Read/Write" start="0x20000000+0x40000/2" name="D1TCM" />
  <MemorySegment size="$(OCRAMSIZE)" access="Read/Write" start="0x2F000000" name="OCRAM" />
  <MemorySegment size="0x100000" access="Read/Write" start="0x40000000" name="PERIPHERALS" />
  <MemorySegment size="0x100000" access="Read/Write" start="0xE0000000" name="PPB" />
</Root>
